.gitignore
CHANGES.txt
LICENSE.txt
MANIFEST.in
README.md
README.txt
setup.py
advancedsearchfilter/__init__.py
advancedsearchfilter/templates/admin/advanced_search.html
advancedsearchfilter/templates/advancedsearchfilter/change_list.html
advancedsearchfilter/templatetags/__init__.py
advancedsearchfilter/templatetags/advancedsearchfilter.py
django_advancedsearchfilter.egg-info/PKG-INFO
django_advancedsearchfilter.egg-info/SOURCES.txt
django_advancedsearchfilter.egg-info/dependency_links.txt
django_advancedsearchfilter.egg-info/not-zip-safe
django_advancedsearchfilter.egg-info/requires.txt
django_advancedsearchfilter.egg-info/top_level.txt