Metadata-Version: 1.1
Name: django-advancedsearchfilter
Version: 0.2.3
Summary: Advanced Search Filter for Django Contrib Admin
Home-page: http://github.com/wildcardcorp/django-advancedsearchfilter
Author: Wildcard Corp.
Author-email: corporate@wildcardcorp.com
License: LICENSE.txt
Keywords: web django search
Platform: UNKNOWN
Classifier: Development Status :: 4 - Beta
Classifier: Framework :: Django
Classifier: Intended Audience :: Developers
Classifier: License :: OSI Approved :: MIT License
Classifier: Natural Language :: English
Classifier: Programming Language :: Python
Classifier: Topic :: Internet :: WWW/HTTP
